baleen/__init__.py
baleen/config.py
baleen/exceptions.py
baleen/export.py
baleen/feed.py
baleen/ingest.py
baleen/models.py
baleen/opml.py
baleen/version.py
baleen/wrangle.py
baleen/console/__init__.py
baleen/console/app.py
baleen/console/utils.py
baleen/console/commands/__init__.py
baleen/console/commands/export.py
baleen/console/commands/ingest.py
baleen/console/commands/load.py
baleen/console/commands/run.py
baleen/console/commands/serve.py
baleen/console/commands/summary.py
baleen/utils/__init__.py
baleen/utils/decorators.py
baleen/utils/logger.py
baleen/utils/mongolog.py
baleen/utils/timez.py
baleen/www/__init__.py
baleen/www/app.py
baleen-0.3.3.data/scripts/baleen
baleen-0.3.3.dist-info/DESCRIPTION.rst
baleen-0.3.3.dist-info/METADATA
baleen-0.3.3.dist-info/RECORD
baleen-0.3.3.dist-info/WHEEL
baleen-0.3.3.dist-info/metadata.json
baleen-0.3.3.dist-info/top_level.txt
tests/utils_tests/__init__.py
tests/utils_tests/test_decorators.py
tests/utils_tests/test_logger.py
tests/utils_tests/test_mongolog.py
tests/utils_tests/test_timez.py
