Metadata-Version: 2.0
Name: baleen
Version: 0.3.3
Summary: An automated ingestion service for blogs to construct a corpus for NLP research.
Home-page: https://github.com/bbengfort/baleen
Author: Benjamin Bengfort
Author-email: benjamin@bengfort.com
License: MIT
Download-URL: https://github.com/bbengfort/baleen/tarball/v0.3.3
Keywords: nlp,baleen,ingestion,blogs,rss
Platform: UNKNOWN
Classifier: Development Status :: 4 - Beta
Classifier: Environment :: Console
Classifier: Intended Audience :: Developers
Classifier: License :: OSI Approved :: MIT License
Classifier: Natural Language :: English
Classifier: Operating System :: OS Independent
Classifier: Programming Language :: Python
Classifier: Programming Language :: Python :: 2.7
Classifier: Topic :: Software Development
Classifier: Topic :: Software Development :: Libraries :: Python Modules
Classifier: Topic :: Utilities
Requires-Dist: Flask (==0.10.1)
Requires-Dist: Flask-Admin (==1.4.0)
Requires-Dist: Flask-Humanize (==0.3.0)
Requires-Dist: Flask-WTF (==0.12)
Requires-Dist: Jinja2 (==2.8)
Requires-Dist: MarkupSafe (==0.23)
Requires-Dist: PyYAML (==3.11)
Requires-Dist: WTForms (==2.1)
Requires-Dist: Werkzeug (==0.11.5)
Requires-Dist: beautifulsoup4 (==4.4.1)
Requires-Dist: blinker (==1.4)
Requires-Dist: colorama (==0.3.6)
Requires-Dist: commis (==0.2)
Requires-Dist: confire (==0.2.0)
Requires-Dist: enum34 (==1.1.3)
Requires-Dist: feedparser (==5.2.1)
Requires-Dist: flask-mongoengine (==0.7.5)
Requires-Dist: humanize (==0.5.1)
Requires-Dist: itsdangerous (==0.24)
Requires-Dist: lxml (==3.5.0)
Requires-Dist: mongoengine (==0.10.6)
Requires-Dist: pymongo (==3.2.1)
Requires-Dist: python-dateutil (==2.4.2)
Requires-Dist: requests (==2.9.1)
Requires-Dist: schedule (==0.3.2)
Requires-Dist: six (==1.10.0)
